{
  "ts": "2025-08-29T14:48:30.732227+05:30",
  "symbol": "BANKNIFTY",
  "spot": 53709.95,
  "vwap_spot": NaN,
  "vwap_fut": 54310.592897785034,
  "rsi5": 37.12172299526778,
  "macd": -45.79791804878914,
  "macd_signal": -42.03209491286097,
  "adx5": 24.381985022104452,
  "pcr": 0.873,
  "dpcr": 0.0,
  "dpcr_z": 0.16,
  "maxpain": 55000,
  "dist_to_mp": -1290.1,
  "atr_d": 425.7,
  "vnd": 3.03,
  "mph_pts_per_hr": -0.0,
  "mph_norm": -0.0,
  "atm": 53700,
  "atm_iv": 10.79,
  "div": -0.1,
  "iv_z": -1.55,
  "iv_pct_hint": 6.2,
  "basis": 390.5,
  "ssd": 12.9,
  "pdist_pct": 2.4,
  "sma20": 53788.79,
  "ema20": 53788.36,
  "bb_pos": -0.82,
  "ichimoku_trend": -1.0,
  "pivot": NaN,
  "fib382": 53923.4,
  "fib618": 53822.95,
  "bullish_signals": 0,
  "bearish_signals": 7,
  "ce_oi_shift": -1295.0,
  "pe_oi_shift": -420.0,
  "scen_probs": {
    "Short-cover reversion up": 0.131,
    "Bear migration": 0.252,
    "Bull migration / gamma carry": 0.158,
    "Pin & decay day (IV crush)": 0.198,
    "Squeeze continuation (one-way)": 0.135,
    "Event knee-jerk then revert": 0.125
  },
  "scen_top": "Bear migration",
  "trade": {
    "action": "BUY_PE",
    "instrument": "PE 53500",
    "entry": "VWAP fail + 5m close below VWAP",
    "sl": "Above VWAP or last LH",
    "targets": [
      "53665",
      "54900"
    ],
    "invalidate": "VWAP reclaim + \u0394PCR z \u2265 +0.5"
  },
  "eq_line": "Equivalence: 200 NIFTY \u2248 652 BANKNIFTY (ATR_NF=130, ATR_BN=425)"
}